graphreveal/__init__.py
graphreveal/cli.py
graphreveal/db_creator/__init__.py
graphreveal/db_creator/create.py
graphreveal/db_creator/util.py
graphreveal/db_creator/data/graph1.g6
graphreveal/db_creator/data/graph2.g6
graphreveal/db_creator/data/graph3.g6
graphreveal/db_creator/data/graph4.g6
graphreveal/db_creator/data/graph5.g6
graphreveal/db_creator/data/graph6.g6
graphreveal/db_creator/data/graph7.g6
graphreveal/db_creator/data/graph8.g6
graphreveal/db_creator/data/graph9.g6
graphreveal/translator/QueryLexer.g4
graphreveal/translator/QueryParser.g4
graphreveal/translator/QueryTranslator.py
graphreveal/translator/__init__.py
graphreveal/translator/translate.py
graphreveal/translator/generated/QueryLexer.py
graphreveal/translator/generated/QueryParser.py
graphreveal/translator/generated/QueryParserVisitor.py
graphreveal-1.0.0.dist-info/METADATA
graphreveal-1.0.0.dist-info/WHEEL
graphreveal-1.0.0.dist-info/entry_points.txt
graphreveal-1.0.0.dist-info/licenses/LICENSE
graphreveal-1.0.0.dist-info/RECORD
