Metadata-Version: 2.4
Name: graphreveal
Version: 1.0.0
Summary: Small graphs database and search system
Project-URL: Changelog, https://github.com/mdbrnowski/GraphReveal/releases
Project-URL: Source, https://github.com/mdbrnowski/GraphReveal
Author-email: Michał Dobranowski <mdbrnowski@gmail.com>
License-Expression: MIT
License-File: LICENSE
Keywords: database,graph-theory,graphs
Classifier: Development Status :: 5 - Production/Stable
Classifier: Environment :: Console
Classifier: License :: OSI Approved :: MIT License
Classifier: Operating System :: MacOS
Classifier: Operating System :: Microsoft :: Windows
Classifier: Operating System :: POSIX :: Linux
Classifier: Programming Language :: Python
Classifier: Programming Language :: Python :: 3
Classifier: Programming Language :: Python :: 3.10
Classifier: Programming Language :: Python :: 3.11
Classifier: Programming Language :: Python :: 3.12
Classifier: Programming Language :: Python :: 3.13
Classifier: Programming Language :: Python :: 3.14
Classifier: Topic :: Database
Classifier: Topic :: Scientific/Engineering :: Mathematics
Requires-Python: >=3.10
Requires-Dist: antlr4-python3-runtime>=4.13.2
Requires-Dist: networkx>=3.4.2
Requires-Dist: platformdirs>=4.3.6
Requires-Dist: rich>=13.9.4
Requires-Dist: typer>=0.17.4
